playatanu v0.0.5.zip
playatanu/__init__.py
playatanu/models/__init__.py
playatanu/models/anet7.py
playatanu/models/anet/ANet7.py
playatanu/models/anet/__init__.py
playatanu/utils/__init__.py
playatanu/utils/image/Image.py
playatanu/utils/image/__init__.py
playatanu/utils/plot/__init__.py
playatanu-0.0.7.dist-info/LICENSE
playatanu-0.0.7.dist-info/METADATA
playatanu-0.0.7.dist-info/WHEEL
playatanu-0.0.7.dist-info/top_level.txt
playatanu-0.0.7.dist-info/RECORD
