Metadata-Version: 2.1
Name: playatanu
Version: 0.0.7
Summary: machine learning toolkit
Home-page: https://github.com/playatanu/py-playatanu
Author: Atanu Debnath
Author-email: playatanu@gmail.com
License: MIT
Classifier: Development Status :: 5 - Production/Stable
Classifier: Programming Language :: Python :: 3
Classifier: Operating System :: OS Independent
Classifier: License :: OSI Approved :: MIT License
License-File: LICENSE
